streamlit_shap/__init__.py
streamlit_shap-1.0.2.dist-info/LICENSE
streamlit_shap-1.0.2.dist-info/METADATA
streamlit_shap-1.0.2.dist-info/WHEEL
streamlit_shap-1.0.2.dist-info/top_level.txt
streamlit_shap-1.0.2.dist-info/RECORD
