Metadata-Version: 2.1
Name: streamlit-shap
Version: 1.0.2
Summary: Streamlit component for SHAP
Home-page: https://github.com/snehankekre/streamlit-shap
Author: Snehan Kekre
Author-email: snehan@streamlit.io
License: UNKNOWN
Platform: UNKNOWN
Classifier: Programming Language :: Python :: 3
Classifier: Operating System :: OS Independent
Requires-Python: >=3.6
License-File: LICENSE
